{
  "button":[
    {
      "type":"view",
      "name":"在线客服",
      "url":"http://www.hkcna.hk"
    },
    {
      "name":"功能服务",
      "sub_button":[
        {
          "type":"view",
          "name":"进度查询",
          "url":"http://39.107.41.253/nx/jump/jumpToScheduleQuery"
        },
        {
          "type":"view",
          "name":"APP下载",
          "url":"http://39.107.41.253/nx/jump/jumpToAppDownload"
        }]
    },
    {
      "name":"诺信学院",
      "sub_button":[
        {
          "type":"view",
          "name":"相关知识",
          "url":"http://39.107.41.253/nx/jump/jumpToLoanRelatedInformation"
        },
        {
          "type":"view",
          "name":"大数据",
          "url":"http://39.107.41.253/nx/jump/jumpToBigData"
        },{
          "type":"view",
          "name":"征信",
          "url":"http://39.107.41.253/nx/jump/jumpToCreditReporting"
        }]
    }
  ]
}